mhered_test_pkg/__init__.py
mhered_test_pkg/__main__.py
mhered_test_pkg-0.1.10.dist-info/entry_points.txt
mhered_test_pkg-0.1.10.dist-info/LICENSE.md
mhered_test_pkg-0.1.10.dist-info/WHEEL
mhered_test_pkg-0.1.10.dist-info/METADATA
mhered_test_pkg-0.1.10.dist-info/RECORD
