Metadata-Version: 2.1
Name: mhered-test-pkg
Version: 0.1.10
Summary: A simple demo package to practice how to create python packages.
Author: Manuel Heredia
Author-email: manolo.heredia@gmail.com
Requires-Python: >=3.8,<4.0
Classifier: Programming Language :: Python :: 3
Classifier: Programming Language :: Python :: 3.10
Classifier: Programming Language :: Python :: 3.8
Classifier: Programming Language :: Python :: 3.9
